iscc_core/.gitignore
iscc_core/__init__.py
iscc_core/__main__.py
iscc_core/cdc.cpython-313-darwin.so
iscc_core/cdc.pxd
iscc_core/cdc.py
iscc_core/check.py
iscc_core/code_content_audio.py
iscc_core/code_content_image.py
iscc_core/code_content_mixed.py
iscc_core/code_content_text.py
iscc_core/code_content_video.py
iscc_core/code_data.py
iscc_core/code_flake.py
iscc_core/code_instance.py
iscc_core/code_meta.py
iscc_core/codec.py
iscc_core/conformance.py
iscc_core/constants.py
iscc_core/data.json
iscc_core/dct.cpython-313-darwin.so
iscc_core/dct.py
iscc_core/fastcdc.pyx
iscc_core/iscc_code.py
iscc_core/iscc_id.py
iscc_core/minhash.cpython-313-darwin.so
iscc_core/minhash.pxd
iscc_core/minhash.py
iscc_core/models.py
iscc_core/options.py
iscc_core/simhash.cpython-313-darwin.so
iscc_core/simhash.pxd
iscc_core/simhash.py
iscc_core/utils.py
iscc_core/wtahash.cpython-313-darwin.so
iscc_core/wtahash.py
iscc_core/cdc.c
iscc_core/dct.c
iscc_core/minhash.c
iscc_core/simhash.c
iscc_core/wtahash.c
iscc_core-1.2.2.dist-info/LICENSE
iscc_core-1.2.2.dist-info/METADATA
iscc_core-1.2.2.dist-info/WHEEL
iscc_core-1.2.2.dist-info/RECORD
