Metadata-Version: 2.1
Name: iscc-core
Version: 1.2.2
Summary: ISCC - Core Algorithms
Home-page: https://iscc.codes
License: Apache-2.0
Keywords: iscc,identifier,media,hash,similarity
Author: Titusz
Author-email: tp@iscc.io
Requires-Python: >=3.9,<4.0
Classifier: Development Status :: 4 - Beta
Classifier: Intended Audience :: Developers
Classifier: Intended Audience :: Science/Research
Classifier: License :: OSI Approved :: Apache Software License
Classifier: License :: OSI Approved :: BSD License
Classifier: Natural Language :: English
Classifier: Operating System :: OS Independent
Classifier: Programming Language :: Cython
Classifier: Programming Language :: Python :: 3
Classifier: Programming Language :: Python :: 3.9
Classifier: Programming Language :: Python :: 3.10
Classifier: Programming Language :: Python :: 3.11
Classifier: Programming Language :: Python :: 3.12
Classifier: Programming Language :: Python :: 3.13
Classifier: Topic :: Multimedia
Classifier: Topic :: Multimedia :: Graphics
Classifier: Topic :: Multimedia :: Sound/Audio
Classifier: Topic :: Multimedia :: Video
Classifier: Topic :: Scientific/Engineering :: Image Recognition
Classifier: Topic :: Scientific/Engineering :: Information Analysis
Classifier: Topic :: Software Development :: Libraries :: Python Modules
Classifier: Topic :: Text Processing :: Indexing
Provides-Extra: turbo
Requires-Dist: base58
Requires-Dist: bitarray
Requires-Dist: blake3
Requires-Dist: cython (>=3) ; extra == "turbo"
Requires-Dist: data-url (>=1.1.0)
Requires-Dist: jcs
Requires-Dist: loguru
Requires-Dist: more-itertools
Requires-Dist: pybase64
Requires-Dist: pydantic
Requires-Dist: python-dotenv
Requires-Dist: uvarint
Requires-Dist: xxhash
Project-URL: Bug Tracker, https://github.com/iscc/iscc-core/issues
Project-URL: Changelog, https://core.iscc.codes/changelog
Project-URL: Coverage, https://app.codecov.io/gh/iscc/iscc-core
Project-URL: Documentation, https://core.iscc.codes/
Project-URL: Donate, https://iscc.foundation/support
Project-URL: Repository, https://github.com/iscc/iscc-core
Project-URL: Twitter, https://twitter.com/iscc_foundation
